demonlist/__init__.py
demonlist/client.py
demonlist/demonlist.py
demonlist/endpoints.py
demonlist/enums.py
demonlist/exceptions.py
demonlist/utils.py
demonlist-0.11.dist-info/LICENSE
demonlist-0.11.dist-info/METADATA
demonlist-0.11.dist-info/WHEEL
demonlist-0.11.dist-info/top_level.txt
demonlist-0.11.dist-info/RECORD
