Metadata-Version: 2.1
Name: demonlist
Version: 0.11
Summary: Asynchronous wrapper for the https://demonlist.org/ API
Home-page: https://github.com/K1BeR/demonlist-api
Author: Kirill Korolev
Author-email: k1ber@protonmail.com
License: UNKNOWN
Platform: UNKNOWN
Classifier: Programming Language :: Python :: 3.7
License-File: LICENSE
Requires-Dist: aiohttp
Requires-Dist: beautifulsoup4
Requires-Dist: lxml
Requires-Dist: urllib3
